tool_hub/__init__.py
tool_hub/_version.py
tool_hub/core.py
tool_hub/models.py
seer_tool_hub-0.0.3.dist-info/METADATA
seer_tool_hub-0.0.3.dist-info/WHEEL
seer_tool_hub-0.0.3.dist-info/top_level.txt
seer_tool_hub-0.0.3.dist-info/RECORD
