Metadata-Version: 2.4
Name: seer-tool-hub
Version: 0.0.3
Summary: A Hub & Spoke tool selection engine for AI agents with Pinecone vector store
Author-email: Akshay Sharma <akshay@getseer.dev>
Project-URL: Homepage, https://github.com/seer-engg/tool-hub
Project-URL: Documentation, https://github.com/seer-engg/tool-hub#readme
Project-URL: Repository, https://github.com/seer-engg/tool-hub
Project-URL: Issues, https://github.com/seer-engg/tool-hub/issues
Requires-Python: >=3.9
Requires-Dist: openai>=2.8.1
Requires-Dist: pydantic>=2.12.4
Requires-Dist: python-dotenv>=1.2.1
Requires-Dist: tqdm>=4.0.0
Provides-Extra: dev
Requires-Dist: pytest; extra == "dev"
Requires-Dist: python-dotenv; extra == "dev"
Requires-Dist: black; extra == "dev"
Requires-Dist: isort; extra == "dev"
Requires-Dist: composio==0.9.4; extra == "dev"
Requires-Dist: composio-langchain==0.9.4; extra == "dev"
Requires-Dist: pinecone<8.0.0; extra == "dev"
Requires-Dist: langchain-pinecone>=0.2.13; extra == "dev"
Requires-Dist: setuptools-scm>=8; extra == "dev"
